{
  "rows": [
    {
      "character_id": "shroomancer",
      "completed_nodes": 7,
      "damage_dealt": 150,
      "damage_taken": 90,
      "deck_size": 11,
      "fights_won": 3,
      "gold": 82,
      "outcome": "defeat",
      "policy": "random",
      "relic_count": 2,
      "seed": 7680022,
      "steps": 95,
      "total_reward": -29.859999999999992
    },
    {
      "character_id": "shroomancer",
      "completed_nodes": 7,
      "damage_dealt": 267,
      "damage_taken": 79,
      "deck_size": 15,
      "fights_won": 6,
      "gold": 203,
      "outcome": "defeat",
      "policy": "heuristic",
      "relic_count": 0,
      "seed": 7680022,
      "steps": 145,
      "total_reward": 8.469999999999981
    },
    {
      "character_id": "shroomancer",
      "completed_nodes": 9,
      "damage_dealt": 312,
      "damage_taken": 79,
      "deck_size": 16,
      "fights_won": 6,
      "gold": 198,
      "outcome": "defeat",
      "policy": "linear_q",
      "relic_count": 1,
      "seed": 7680022,
      "steps": 137,
      "total_reward": 11.889999999999965
    },
    {
      "character_id": "shroomancer",
      "completed_nodes": 9,
      "damage_dealt": 253,
      "damage_taken": 90,
      "deck_size": 14,
      "fights_won": 4,
      "gold": 133,
      "outcome": "defeat",
      "policy": "random",
      "relic_count": 2,
      "seed": 7680023,
      "steps": 140,
      "total_reward": -12.470000000000049
    },
    {
      "character_id": "shroomancer",
      "completed_nodes": 9,
      "damage_dealt": 299,
      "damage_taken": 72,
      "deck_size": 14,
      "fights_won": 4,
      "gold": 137,
      "outcome": "defeat",
      "policy": "heuristic",
      "relic_count": 3,
      "seed": 7680023,
      "steps": 126,
      "total_reward": -1.8100000000000307
    },
    {
      "character_id": "shroomancer",
      "completed_nodes": 7,
      "damage_dealt": 178,
      "damage_taken": 72,
      "deck_size": 12,
      "fights_won": 3,
      "gold": 102,
      "outcome": "defeat",
      "policy": "linear_q",
      "relic_count": 2,
      "seed": 7680023,
      "steps": 72,
      "total_reward": -18.460000000000015
    },
    {
      "character_id": "shroomancer",
      "completed_nodes": 9,
      "damage_dealt": 212,
      "damage_taken": 72,
      "deck_size": 13,
      "fights_won": 4,
      "gold": 134,
      "outcome": "defeat",
      "policy": "random",
      "relic_count": 3,
      "seed": 7680024,
      "steps": 116,
      "total_reward": -5.690000000000026
    },
    {
      "character_id": "shroomancer",
      "completed_nodes": 9,
      "damage_dealt": 296,
      "damage_taken": 72,
      "deck_size": 16,
      "fights_won": 5,
      "gold": 165,
      "outcome": "defeat",
      "policy": "heuristic",
      "relic_count": 3,
      "seed": 7680024,
      "steps": 150,
      "total_reward": 4.96999999999997
    },
    {
      "character_id": "shroomancer",
      "completed_nodes": 9,
      "damage_dealt": 311,
      "damage_taken": 72,
      "deck_size": 16,
      "fights_won": 5,
      "gold": 158,
      "outcome": "defeat",
      "policy": "linear_q",
      "relic_count": 3,
      "seed": 7680024,
      "steps": 155,
      "total_reward": 6.909999999999947
    },
    {
      "character_id": "shroomancer",
      "completed_nodes": 4,
      "damage_dealt": 140,
      "damage_taken": 72,
      "deck_size": 13,
      "fights_won": 4,
      "gold": 128,
      "outcome": "defeat",
      "policy": "random",
      "relic_count": 0,
      "seed": 7680025,
      "steps": 104,
      "total_reward": -20.069999999999997
    },
    {
      "character_id": "shroomancer",
      "completed_nodes": 9,
      "damage_dealt": 341,
      "damage_taken": 72,
      "deck_size": 16,
      "fights_won": 6,
      "gold": 182,
      "outcome": "defeat",
      "policy": "heuristic",
      "relic_count": 3,
      "seed": 7680025,
      "steps": 150,
      "total_reward": 20.39999999999995
    },
    {
      "character_id": "shroomancer",
      "completed_nodes": 9,
      "damage_dealt": 301,
      "damage_taken": 72,
      "deck_size": 16,
      "fights_won": 6,
      "gold": 182,
      "outcome": "defeat",
      "policy": "linear_q",
      "relic_count": 3,
      "seed": 7680025,
      "steps": 129,
      "total_reward": 20.229999999999976
    },
    {
      "character_id": "shroomancer",
      "completed_nodes": 6,
      "damage_dealt": 178,
      "damage_taken": 90,
      "deck_size": 13,
      "fights_won": 4,
      "gold": 144,
      "outcome": "defeat",
      "policy": "random",
      "relic_count": 0,
      "seed": 7680026,
      "steps": 177,
      "total_reward": -24.180000000000046
    },
    {
      "character_id": "shroomancer",
      "completed_nodes": 9,
      "damage_dealt": 373,
      "damage_taken": 120,
      "deck_size": 16,
      "fights_won": 6,
      "gold": 198,
      "outcome": "defeat",
      "policy": "heuristic",
      "relic_count": 1,
      "seed": 7680026,
      "steps": 206,
      "total_reward": 2.639999999999965
    },
    {
      "character_id": "shroomancer",
      "completed_nodes": 10,
      "damage_dealt": 551,
      "damage_taken": 102,
      "deck_size": 17,
      "fights_won": 7,
      "gold": 335,
      "outcome": "win",
      "policy": "linear_q",
      "relic_count": 1,
      "seed": 7680026,
      "steps": 236,
      "total_reward": 115.95999999999992
    },
    {
      "character_id": "shroomancer",
      "completed_nodes": 9,
      "damage_dealt": 270,
      "damage_taken": 73,
      "deck_size": 14,
      "fights_won": 5,
      "gold": 155,
      "outcome": "defeat",
      "policy": "random",
      "relic_count": 3,
      "seed": 7680027,
      "steps": 139,
      "total_reward": 3.379999999999974
    },
    {
      "character_id": "shroomancer",
      "completed_nodes": 9,
      "damage_dealt": 265,
      "damage_taken": 78,
      "deck_size": 13,
      "fights_won": 3,
      "gold": 142,
      "outcome": "defeat",
      "policy": "heuristic",
      "relic_count": 5,
      "seed": 7680027,
      "steps": 100,
      "total_reward": -10.330000000000005
    },
    {
      "character_id": "shroomancer",
      "completed_nodes": 10,
      "damage_dealt": 284,
      "damage_taken": 54,
      "deck_size": 13,
      "fights_won": 4,
      "gold": 202,
      "outcome": "win",
      "policy": "linear_q",
      "relic_count": 5,
      "seed": 7680027,
      "steps": 106,
      "total_reward": 100.26999999999995
    },
    {
      "character_id": "shroomancer",
      "completed_nodes": 9,
      "damage_dealt": 222,
      "damage_taken": 102,
      "deck_size": 12,
      "fights_won": 5,
      "gold": 173,
      "outcome": "defeat",
      "policy": "random",
      "relic_count": 1,
      "seed": 7680028,
      "steps": 169,
      "total_reward": -10.24000000000003
    },
    {
      "character_id": "shroomancer",
      "completed_nodes": 10,
      "damage_dealt": 417,
      "damage_taken": 78,
      "deck_size": 15,
      "fights_won": 7,
      "gold": 299,
      "outcome": "win",
      "policy": "heuristic",
      "relic_count": 1,
      "seed": 7680028,
      "steps": 179,
      "total_reward": 114.78999999999996
    },
    {
      "character_id": "shroomancer",
      "completed_nodes": 9,
      "damage_dealt": 399,
      "damage_taken": 90,
      "deck_size": 16,
      "fights_won": 6,
      "gold": 181,
      "outcome": "defeat",
      "policy": "linear_q",
      "relic_count": 1,
      "seed": 7680028,
      "steps": 168,
      "total_reward": 7.7899999999999565
    },
    {
      "character_id": "shroomancer",
      "completed_nodes": 5,
      "damage_dealt": 161,
      "damage_taken": 72,
      "deck_size": 13,
      "fights_won": 3,
      "gold": 103,
      "outcome": "defeat",
      "policy": "random",
      "relic_count": 1,
      "seed": 7680029,
      "steps": 119,
      "total_reward": -19.83000000000001
    },
    {
      "character_id": "shroomancer",
      "completed_nodes": 9,
      "damage_dealt": 336,
      "damage_taken": 72,
      "deck_size": 18,
      "fights_won": 7,
      "gold": 218,
      "outcome": "defeat",
      "policy": "heuristic",
      "relic_count": 0,
      "seed": 7680029,
      "steps": 170,
      "total_reward": 27.49999999999993
    },
    {
      "character_id": "shroomancer",
      "completed_nodes": 9,
      "damage_dealt": 433,
      "damage_taken": 72,
      "deck_size": 16,
      "fights_won": 6,
      "gold": 184,
      "outcome": "defeat",
      "policy": "linear_q",
      "relic_count": 2,
      "seed": 7680029,
      "steps": 140,
      "total_reward": 22.599999999999937
    },
    {
      "character_id": "shroomancer",
      "completed_nodes": 9,
      "damage_dealt": 192,
      "damage_taken": 90,
      "deck_size": 14,
      "fights_won": 5,
      "gold": 170,
      "outcome": "defeat",
      "policy": "random",
      "relic_count": 0,
      "seed": 7680030,
      "steps": 146,
      "total_reward": -6.390000000000036
    },
    {
      "character_id": "shroomancer",
      "completed_nodes": 9,
      "damage_dealt": 345,
      "damage_taken": 81,
      "deck_size": 16,
      "fights_won": 6,
      "gold": 196,
      "outcome": "defeat",
      "policy": "heuristic",
      "relic_count": 1,
      "seed": 7680030,
      "steps": 217,
      "total_reward": 13.289999999999885
    },
    {
      "character_id": "shroomancer",
      "completed_nodes": 10,
      "damage_dealt": 461,
      "damage_taken": 80,
      "deck_size": 16,
      "fights_won": 7,
      "gold": 328,
      "outcome": "win",
      "policy": "linear_q",
      "relic_count": 1,
      "seed": 7680030,
      "steps": 185,
      "total_reward": 121.92999999999994
    },
    {
      "character_id": "shroomancer",
      "completed_nodes": 8,
      "damage_dealt": 227,
      "damage_taken": 90,
      "deck_size": 14,
      "fights_won": 5,
      "gold": 154,
      "outcome": "defeat",
      "policy": "random",
      "relic_count": 1,
      "seed": 7680031,
      "steps": 154,
      "total_reward": -3.780000000000051
    },
    {
      "character_id": "shroomancer",
      "completed_nodes": 9,
      "damage_dealt": 370,
      "damage_taken": 74,
      "deck_size": 17,
      "fights_won": 7,
      "gold": 252,
      "outcome": "defeat",
      "policy": "heuristic",
      "relic_count": 1,
      "seed": 7680031,
      "steps": 200,
      "total_reward": 29.149999999999928
    },
    {
      "character_id": "shroomancer",
      "completed_nodes": 10,
      "damage_dealt": 475,
      "damage_taken": 79,
      "deck_size": 16,
      "fights_won": 7,
      "gold": 302,
      "outcome": "win",
      "policy": "linear_q",
      "relic_count": 1,
      "seed": 7680031,
      "steps": 193,
      "total_reward": 119.58999999999995
    },
    {
      "character_id": "shroomancer",
      "completed_nodes": 7,
      "damage_dealt": 217,
      "damage_taken": 89,
      "deck_size": 14,
      "fights_won": 5,
      "gold": 155,
      "outcome": "defeat",
      "policy": "random",
      "relic_count": 1,
      "seed": 7680032,
      "steps": 173,
      "total_reward": -7.140000000000008
    },
    {
      "character_id": "shroomancer",
      "completed_nodes": 9,
      "damage_dealt": 336,
      "damage_taken": 72,
      "deck_size": 16,
      "fights_won": 6,
      "gold": 190,
      "outcome": "defeat",
      "policy": "heuristic",
      "relic_count": 2,
      "seed": 7680032,
      "steps": 183,
      "total_reward": 19.549999999999947
    },
    {
      "character_id": "shroomancer",
      "completed_nodes": 9,
      "damage_dealt": 337,
      "damage_taken": 72,
      "deck_size": 16,
      "fights_won": 6,
      "gold": 192,
      "outcome": "defeat",
      "policy": "linear_q",
      "relic_count": 2,
      "seed": 7680032,
      "steps": 160,
      "total_reward": 20.31999999999995
    },
    {
      "character_id": "shroomancer",
      "completed_nodes": 7,
      "damage_dealt": 243,
      "damage_taken": 72,
      "deck_size": 15,
      "fights_won": 6,
      "gold": 191,
      "outcome": "defeat",
      "policy": "random",
      "relic_count": 0,
      "seed": 7680033,
      "steps": 151,
      "total_reward": 12.289999999999964
    },
    {
      "character_id": "shroomancer",
      "completed_nodes": 9,
      "damage_dealt": 462,
      "damage_taken": 72,
      "deck_size": 18,
      "fights_won": 8,
      "gold": 249,
      "outcome": "defeat",
      "policy": "heuristic",
      "relic_count": 1,
      "seed": 7680033,
      "steps": 189,
      "total_reward": 42.399999999999956
    },
    {
      "character_id": "shroomancer",
      "completed_nodes": 8,
      "damage_dealt": 311,
      "damage_taken": 72,
      "deck_size": 17,
      "fights_won": 7,
      "gold": 224,
      "outcome": "defeat",
      "policy": "linear_q",
      "relic_count": 1,
      "seed": 7680033,
      "steps": 164,
      "total_reward": 27.989999999999974
    },
    {
      "character_id": "shroomancer",
      "completed_nodes": 9,
      "damage_dealt": 316,
      "damage_taken": 72,
      "deck_size": 16,
      "fights_won": 8,
      "gold": 228,
      "outcome": "defeat",
      "policy": "random",
      "relic_count": 1,
      "seed": 7680034,
      "steps": 255,
      "total_reward": 34.16999999999991
    },
    {
      "character_id": "shroomancer",
      "completed_nodes": 10,
      "damage_dealt": 370,
      "damage_taken": 89,
      "deck_size": 15,
      "fights_won": 6,
      "gold": 277,
      "outcome": "win",
      "policy": "heuristic",
      "relic_count": 3,
      "seed": 7680034,
      "steps": 161,
      "total_reward": 105.32999999999994
    },
    {
      "character_id": "shroomancer",
      "completed_nodes": 9,
      "damage_dealt": 325,
      "damage_taken": 76,
      "deck_size": 15,
      "fights_won": 5,
      "gold": 153,
      "outcome": "defeat",
      "policy": "linear_q",
      "relic_count": 3,
      "seed": 7680034,
      "steps": 166,
      "total_reward": 6.759999999999927
    },
    {
      "character_id": "shroomancer",
      "completed_nodes": 4,
      "damage_dealt": 108,
      "damage_taken": 72,
      "deck_size": 13,
      "fights_won": 2,
      "gold": 61,
      "outcome": "defeat",
      "policy": "random",
      "relic_count": 1,
      "seed": 7680035,
      "steps": 91,
      "total_reward": -38.34999999999999
    },
    {
      "character_id": "shroomancer",
      "completed_nodes": 9,
      "damage_dealt": 271,
      "damage_taken": 90,
      "deck_size": 14,
      "fights_won": 3,
      "gold": 104,
      "outcome": "defeat",
      "policy": "heuristic",
      "relic_count": 4,
      "seed": 7680035,
      "steps": 98,
      "total_reward": -21.74000000000002
    },
    {
      "character_id": "shroomancer",
      "completed_nodes": 10,
      "damage_dealt": 329,
      "damage_taken": 86,
      "deck_size": 14,
      "fights_won": 4,
      "gold": 232,
      "outcome": "win",
      "policy": "linear_q",
      "relic_count": 4,
      "seed": 7680035,
      "steps": 102,
      "total_reward": 85.73999999999998
    },
    {
      "character_id": "shroomancer",
      "completed_nodes": 3,
      "damage_dealt": 120,
      "damage_taken": 72,
      "deck_size": 13,
      "fights_won": 3,
      "gold": 96,
      "outcome": "defeat",
      "policy": "random",
      "relic_count": 0,
      "seed": 7680036,
      "steps": 111,
      "total_reward": -30.660000000000004
    },
    {
      "character_id": "shroomancer",
      "completed_nodes": 10,
      "damage_dealt": 318,
      "damage_taken": 38,
      "deck_size": 15,
      "fights_won": 5,
      "gold": 156,
      "outcome": "win",
      "policy": "heuristic",
      "relic_count": 2,
      "seed": 7680036,
      "steps": 121,
      "total_reward": 111.24
    },
    {
      "character_id": "shroomancer",
      "completed_nodes": 10,
      "damage_dealt": 298,
      "damage_taken": 65,
      "deck_size": 13,
      "fights_won": 5,
      "gold": 252,
      "outcome": "win",
      "policy": "linear_q",
      "relic_count": 2,
      "seed": 7680036,
      "steps": 111,
      "total_reward": 99.86999999999999
    },
    {
      "character_id": "shroomancer",
      "completed_nodes": 9,
      "damage_dealt": 277,
      "damage_taken": 72,
      "deck_size": 15,
      "fights_won": 6,
      "gold": 176,
      "outcome": "defeat",
      "policy": "random",
      "relic_count": 2,
      "seed": 7680037,
      "steps": 151,
      "total_reward": 18.559999999999967
    },
    {
      "character_id": "shroomancer",
      "completed_nodes": 9,
      "damage_dealt": 317,
      "damage_taken": 72,
      "deck_size": 16,
      "fights_won": 5,
      "gold": 177,
      "outcome": "defeat",
      "policy": "heuristic",
      "relic_count": 3,
      "seed": 7680037,
      "steps": 170,
      "total_reward": 7.1499999999999275
    },
    {
      "character_id": "shroomancer",
      "completed_nodes": 10,
      "damage_dealt": 366,
      "damage_taken": 48,
      "deck_size": 15,
      "fights_won": 6,
      "gold": 331,
      "outcome": "win",
      "policy": "linear_q",
      "relic_count": 3,
      "seed": 7680037,
      "steps": 157,
      "total_reward": 125.38999999999993
    },
    {
      "character_id": "shroomancer",
      "completed_nodes": 9,
      "damage_dealt": 197,
      "damage_taken": 72,
      "deck_size": 14,
      "fights_won": 5,
      "gold": 248,
      "outcome": "defeat",
      "policy": "random",
      "relic_count": 2,
      "seed": 7680038,
      "steps": 154,
      "total_reward": 8.66000000000001
    },
    {
      "character_id": "shroomancer",
      "completed_nodes": 9,
      "damage_dealt": 294,
      "damage_taken": 72,
      "deck_size": 14,
      "fights_won": 4,
      "gold": 130,
      "outcome": "defeat",
      "policy": "heuristic",
      "relic_count": 3,
      "seed": 7680038,
      "steps": 123,
      "total_reward": -0.030000000000050875
    },
    {
      "character_id": "shroomancer",
      "completed_nodes": 10,
      "damage_dealt": 448,
      "damage_taken": 84,
      "deck_size": 16,
      "fights_won": 7,
      "gold": 313,
      "outcome": "win",
      "policy": "linear_q",
      "relic_count": 2,
      "seed": 7680038,
      "steps": 170,
      "total_reward": 128.06999999999994
    },
    {
      "character_id": "shroomancer",
      "completed_nodes": 7,
      "damage_dealt": 204,
      "damage_taken": 90,
      "deck_size": 15,
      "fights_won": 5,
      "gold": 179,
      "outcome": "defeat",
      "policy": "random",
      "relic_count": 0,
      "seed": 7680039,
      "steps": 98,
      "total_reward": -4.500000000000028
    },
    {
      "character_id": "shroomancer",
      "completed_nodes": 9,
      "damage_dealt": 368,
      "damage_taken": 72,
      "deck_size": 17,
      "fights_won": 6,
      "gold": 200,
      "outcome": "defeat",
      "policy": "heuristic",
      "relic_count": 2,
      "seed": 7680039,
      "steps": 210,
      "total_reward": 24.029999999999973
    },
    {
      "character_id": "shroomancer",
      "completed_nodes": 9,
      "damage_dealt": 373,
      "damage_taken": 72,
      "deck_size": 17,
      "fights_won": 6,
      "gold": 223,
      "outcome": "defeat",
      "policy": "linear_q",
      "relic_count": 2,
      "seed": 7680039,
      "steps": 173,
      "total_reward": 23.92999999999995
    },
    {
      "character_id": "shroomancer",
      "completed_nodes": 7,
      "damage_dealt": 234,
      "damage_taken": 72,
      "deck_size": 15,
      "fights_won": 5,
      "gold": 161,
      "outcome": "defeat",
      "policy": "random",
      "relic_count": 1,
      "seed": 7680040,
      "steps": 177,
      "total_reward": 2.4099999999999824
    },
    {
      "character_id": "shroomancer",
      "completed_nodes": 9,
      "damage_dealt": 295,
      "damage_taken": 72,
      "deck_size": 18,
      "fights_won": 7,
      "gold": 234,
      "outcome": "defeat",
      "policy": "heuristic",
      "relic_count": 1,
      "seed": 7680040,
      "steps": 168,
      "total_reward": 25.219999999999963
    },
    {
      "character_id": "shroomancer",
      "completed_nodes": 10,
      "damage_dealt": 516,
      "damage_taken": 27,
      "deck_size": 18,
      "fights_won": 8,
      "gold": 355,
      "outcome": "win",
      "policy": "linear_q",
      "relic_count": 1,
      "seed": 7680040,
      "steps": 265,
      "total_reward": 155.3599999999999
    },
    {
      "character_id": "shroomancer",
      "completed_nodes": 9,
      "damage_dealt": 138,
      "damage_taken": 108,
      "deck_size": 14,
      "fights_won": 2,
      "gold": 12,
      "outcome": "defeat",
      "policy": "random",
      "relic_count": 2,
      "seed": 7680041,
      "steps": 117,
      "total_reward": -44.99999999999999
    },
    {
      "character_id": "shroomancer",
      "completed_nodes": 9,
      "damage_dealt": 239,
      "damage_taken": 88,
      "deck_size": 15,
      "fights_won": 3,
      "gold": 38,
      "outcome": "defeat",
      "policy": "heuristic",
      "relic_count": 3,
      "seed": 7680041,
      "steps": 126,
      "total_reward": -20.10000000000004
    },
    {
      "character_id": "shroomancer",
      "completed_nodes": 10,
      "damage_dealt": 327,
      "damage_taken": 80,
      "deck_size": 14,
      "fights_won": 4,
      "gold": 241,
      "outcome": "win",
      "policy": "linear_q",
      "relic_count": 3,
      "seed": 7680041,
      "steps": 119,
      "total_reward": 89.85999999999999
    }
  ],
  "schema_version": 1,
  "summary": [
    {
      "average_completed_nodes": 9.05,
      "average_damage_dealt": 328.95,
      "average_damage_taken": 76.75,
      "average_deck_size": 15.7,
      "average_fights_won": 5.5,
      "average_gold": 187.35,
      "average_relic_count": 2.1,
      "average_reward": 25.10599999999996,
      "average_steps": 159.6,
      "character_id": "__overall__",
      "defeats": 17,
      "policy": "heuristic",
      "runs": 20,
      "stalls": 0,
      "truncated": 0,
      "win_rate": 0.15,
      "wins": 3
    },
    {
      "average_completed_nodes": 9.05,
      "average_damage_dealt": 328.95,
      "average_damage_taken": 76.75,
      "average_deck_size": 15.7,
      "average_fights_won": 5.5,
      "average_gold": 187.35,
      "average_relic_count": 2.1,
      "average_reward": 25.10599999999996,
      "average_steps": 159.6,
      "character_id": "shroomancer",
      "defeats": 17,
      "policy": "heuristic",
      "runs": 20,
      "stalls": 0,
      "truncated": 0,
      "win_rate": 0.15,
      "wins": 3
    },
    {
      "average_completed_nodes": 9.35,
      "average_damage_dealt": 366.75,
      "average_damage_taken": 72.7,
      "average_deck_size": 15.45,
      "average_fights_won": 5.75,
      "average_gold": 234.4,
      "average_relic_count": 2.15,
      "average_reward": 63.59999999999995,
      "average_steps": 155.4,
      "character_id": "__overall__",
      "defeats": 10,
      "policy": "linear_q",
      "runs": 20,
      "stalls": 0,
      "truncated": 0,
      "win_rate": 0.5,
      "wins": 10
    },
    {
      "average_completed_nodes": 9.35,
      "average_damage_dealt": 366.75,
      "average_damage_taken": 72.7,
      "average_deck_size": 15.45,
      "average_fights_won": 5.75,
      "average_gold": 234.4,
      "average_relic_count": 2.15,
      "average_reward": 63.59999999999995,
      "average_steps": 155.4,
      "character_id": "shroomancer",
      "defeats": 10,
      "policy": "linear_q",
      "runs": 20,
      "stalls": 0,
      "truncated": 0,
      "win_rate": 0.5,
      "wins": 10
    },
    {
      "average_completed_nodes": 7.3,
      "average_damage_dealt": 202.95,
      "average_damage_taken": 81.6,
      "average_deck_size": 13.75,
      "average_fights_won": 4.45,
      "average_gold": 144.15,
      "average_relic_count": 1.15,
      "average_reward": -8.934500000000023,
      "average_steps": 141.85,
      "character_id": "__overall__",
      "defeats": 20,
      "policy": "random",
      "runs": 20,
      "stalls": 0,
      "truncated": 0,
      "win_rate": 0.0,
      "wins": 0
    },
    {
      "average_completed_nodes": 7.3,
      "average_damage_dealt": 202.95,
      "average_damage_taken": 81.6,
      "average_deck_size": 13.75,
      "average_fights_won": 4.45,
      "average_gold": 144.15,
      "average_relic_count": 1.15,
      "average_reward": -8.934500000000023,
      "average_steps": 141.85,
      "character_id": "shroomancer",
      "defeats": 20,
      "policy": "random",
      "runs": 20,
      "stalls": 0,
      "truncated": 0,
      "win_rate": 0.0,
      "wins": 0
    }
  ]
}